{"operation": "dereplicate", "work_directory": "ocean_drep_output", "processors": 6, "debug": false, "length": 50000, "completeness": 75, "contamination": 25, "ignoreGenomeQuality": false, "genomeInfo": "Table3_GenomeStats.csv", "checkM_method": "lineage_wf", "set_recursion": "0", "checkm_group_size": 2000, "S_algorithm": "fastANI", "MASH_sketch": 1000, "SkipMash": false, "SkipSecondary": false, "n_PRESET": "normal", "P_ani": 0.9, "S_ani": 0.95, "cov_thresh": 0.1, "coverage_method": "larger", "clusterAlg": "average", "multiround_primary_clustering": false, "primary_chunksize": 5000, "greedy_secondary_clustering": false, "run_tertiary_clustering": false, "completeness_weight": 1, "contamination_weight": 5, "strain_heterogeneity_weight": 1, "N50_weight": 0.5, "size_weight": 0, "centrality_weight": 1, "extra_weight_table": null, "gen_warnings": false, "warn_dist": 0.25, "warn_sim": 0.98, "warn_aln": 0.25, "skip_plots": false}